CHANGES.rst
DESCRIPTION.rst
LICENSE
MANIFEST.in
README.md
setup.py
src/wai.annotations.imgaug.egg-info/PKG-INFO
src/wai.annotations.imgaug.egg-info/SOURCES.txt
src/wai.annotations.imgaug.egg-info/dependency_links.txt
src/wai.annotations.imgaug.egg-info/entry_points.txt
src/wai.annotations.imgaug.egg-info/namespace_packages.txt
src/wai.annotations.imgaug.egg-info/requires.txt
src/wai.annotations.imgaug.egg-info/top_level.txt
src/wai/annotations/imgaug/isp/__init__.py
src/wai/annotations/imgaug/isp/base/__init__.py
src/wai/annotations/imgaug/isp/base/component/_BaseISP.py
src/wai/annotations/imgaug/isp/base/component/_BaseImageAugmentation.py
src/wai/annotations/imgaug/isp/base/component/__init__.py
src/wai/annotations/imgaug/isp/crop/__init__.py
src/wai/annotations/imgaug/isp/crop/component/_Crop.py
src/wai/annotations/imgaug/isp/crop/component/__init__.py
src/wai/annotations/imgaug/isp/crop/specifier/_CropISPSpecifier.py
src/wai/annotations/imgaug/isp/crop/specifier/__init__.py
src/wai/annotations/imgaug/isp/flip/__init__.py
src/wai/annotations/imgaug/isp/flip/component/_Flip.py
src/wai/annotations/imgaug/isp/flip/component/__init__.py
src/wai/annotations/imgaug/isp/flip/specifier/_FlipISPSpecifier.py
src/wai/annotations/imgaug/isp/flip/specifier/__init__.py
src/wai/annotations/imgaug/isp/gaussian_blur/__init__.py
src/wai/annotations/imgaug/isp/gaussian_blur/component/_GaussianBlur.py
src/wai/annotations/imgaug/isp/gaussian_blur/component/__init__.py
src/wai/annotations/imgaug/isp/gaussian_blur/specifier/_GaussianBlurISPSpecifier.py
src/wai/annotations/imgaug/isp/gaussian_blur/specifier/__init__.py
src/wai/annotations/imgaug/isp/hsl_grayscale/__init__.py
src/wai/annotations/imgaug/isp/hsl_grayscale/component/_HSLGrayScale.py
src/wai/annotations/imgaug/isp/hsl_grayscale/component/__init__.py
src/wai/annotations/imgaug/isp/hsl_grayscale/specifier/_HSLGrayScaleISPSpecifier.py
src/wai/annotations/imgaug/isp/hsl_grayscale/specifier/__init__.py
src/wai/annotations/imgaug/isp/linear_contrast/__init__.py
src/wai/annotations/imgaug/isp/linear_contrast/component/_LinearContrast.py
src/wai/annotations/imgaug/isp/linear_contrast/component/__init__.py
src/wai/annotations/imgaug/isp/linear_contrast/specifier/_LinearContrastISPSpecifier.py
src/wai/annotations/imgaug/isp/linear_contrast/specifier/__init__.py
