Metadata-Version: 2.1
Name: wai.annotations.imgaug
Version: 1.0.5
Summary: Various inline stream processors for image augmentation.
Home-page: https://github.com/waikato-ufdl/wai-annotations-imgaug
Author: Peter Reutemann
Author-email: fracpete@waikato.ac.nz
License: Apache License Version 2.0
Platform: UNKNOWN
Classifier: Development Status :: 4 - Beta
Classifier: License :: OSI Approved :: Apache Software License
Classifier: Topic :: Scientific/Engineering :: Mathematics
Classifier: Programming Language :: Python :: 3
License-File: LICENSE
